tiltlib/__init__.py
tiltlib/axis.py
tiltlib/sample.py
tiltlib/sample_holder.py
tiltlib-0.1.dist-info/METADATA
tiltlib-0.1.dist-info/WHEEL
tiltlib-0.1.dist-info/top_level.txt
tiltlib-0.1.dist-info/RECORD
