Metadata-Version: 2.1
Name: tiltlib
Version: 0.1
Summary: TEM tilt holder scripts
Author-email: Viljar Femoen <viljarjf@stud.ntnu.no>
Classifier: Development Status :: 2 - Pre-Alpha
Classifier: Intended Audience :: Science/Research
Classifier: Topic :: Scientific/Engineering :: Physics
Classifier: Programming Language :: Python :: 3
Classifier: Operating System :: OS Independent
Requires-Python: >=3.8
Requires-Dist: numpy
Requires-Dist: orix
Requires-Dist: matplotlib
Requires-Dist: hyperspy
Requires-Dist: scipy
Provides-Extra: docs
Requires-Dist: sphinx ; extra == 'docs'
Requires-Dist: sphinx-rtd-theme ; extra == 'docs'
Requires-Dist: nbsphinx ; extra == 'docs'
Requires-Dist: IPython ; extra == 'docs'
Requires-Dist: ipykernel ; extra == 'docs'
Provides-Extra: test
Requires-Dist: pytest ; extra == 'test'
Requires-Dist: pytest-xdist ; extra == 'test'
Requires-Dist: filelock ; extra == 'test'
